MANIFEST.in
README.rst
setup.py
ambari/__init__.py
ambari/client.py
ambari/cluster.py
ambari/cmd.py
ambari/stack.py
ambari/test.py
ambari.egg-info/PKG-INFO
ambari.egg-info/SOURCES.txt
ambari.egg-info/dependency_links.txt
ambari.egg-info/entry_points.txt
ambari.egg-info/requires.txt
ambari.egg-info/top_level.txt