Metadata-Version: 1.0
Name: ambari
Version: 0.1.4
Summary: Amabri python client based on ambari rest api.
Home-page: https://github.com/excelwang/ambari-python-client
Author: Excel Wang
Author-email: wanghj@cnic.com
License: Apache-2.0 Licence
Keywords: pip,ambari,packone
Platform: any
